dyapi/__init__.py
dyapi/entities/__init__.py
dyapi/entities/config.py
dyapi/entities/endpoint_settings.py
dyapi/entities/model_settings.py
dyapi/entities/pagination.py
dyapi/implementations/__init__.py
dyapi/implementations/builders/__init__.py
dyapi/implementations/builders/api.py
dyapi/implementations/builders/crud.py
dyapi/implementations/builders/endpoint.py
dyapi/implementations/builders/model.py
dyapi/implementations/storages/__init__.py
dyapi/implementations/storages/exceptions.py
dyapi/implementations/storages/postgres/__init__.py
dyapi/implementations/storages/postgres/base.py
dyapi/implementations/storages/postgres/manager.py
dyapi/interfaces/__init__.py
dyapi/interfaces/builders/__init__.py
dyapi/interfaces/builders/api.py
dyapi/interfaces/builders/crud.py
dyapi/interfaces/builders/endpoint.py
dyapi/interfaces/builders/model.py
dyapi/interfaces/storages/__init__.py
dyapi/interfaces/storages/base.py
dyapi/interfaces/storages/manager.py
dyapi-0.9.4.dist-info/METADATA
dyapi-0.9.4.dist-info/WHEEL
dyapi-0.9.4.dist-info/RECORD
